autogluon.vision-0.5.1-py3.7-nspkg.pth
autogluon/vision/__init__.py
autogluon/vision/version.py
autogluon/vision/_gluoncv/__init__.py
autogluon/vision/_gluoncv/image_classification.py
autogluon/vision/_gluoncv/object_detection.py
autogluon/vision/_gluoncv/utils.py
autogluon/vision/configs/__init__.py
autogluon/vision/configs/presets_configs.py
autogluon/vision/detector/__init__.py
autogluon/vision/detector/detector.py
autogluon/vision/predictor/__init__.py
autogluon/vision/predictor/losses.py
autogluon/vision/predictor/predictor.py
autogluon/vision/utils/__init__.py
autogluon/vision/utils/error_handler.py
autogluon/vision/utils/learning_rate.py
autogluon/vision/utils/pickle.py
autogluon/vision/utils/space_sanitizer.py
autogluon.vision-0.5.1.dist-info/LICENSE
autogluon.vision-0.5.1.dist-info/METADATA
autogluon.vision-0.5.1.dist-info/NOTICE
autogluon.vision-0.5.1.dist-info/WHEEL
autogluon.vision-0.5.1.dist-info/namespace_packages.txt
autogluon.vision-0.5.1.dist-info/top_level.txt
autogluon.vision-0.5.1.dist-info/zip-safe
autogluon.vision-0.5.1.dist-info/RECORD
